Metadata-Version: 1.0
Name: zsyyy
Version: 0.1
Summary: This is an Example Package
Home-page: http://example.com/HelloWorld/
Author: ME
Author-email: me@example.com
License: PSF
Keywords: hello world example examples
Platform: UNKNOWN
